WallaBlur/__init__.py
WallaBlur/__main__.py
WallaBlur/backend.py
WallaBlur/cache.py
WallaBlur/draw.py
WallaBlur-1.0.1.dist-info/LICENSE
WallaBlur-1.0.1.dist-info/METADATA
WallaBlur-1.0.1.dist-info/WHEEL
WallaBlur-1.0.1.dist-info/entry_points.txt
WallaBlur-1.0.1.dist-info/top_level.txt
WallaBlur-1.0.1.dist-info/RECORD
