Metadata-Version: 2.1
Name: WallaBlur
Version: 1.0.1
Summary: blur background on window opening
Home-page: https://github.com/Di-KaZ/WallaBlur
Author: Moussa Fofana
Author-email: moussa.fofana@epitech.eu
License: UNKNOWN
Platform: UNKNOWN
Requires-Python: >=3.6
Requires-Dist: ewmh
